ai_lab_dump.py
ai_lab_dump-0.0.3.dist-info/LICENSE
ai_lab_dump-0.0.3.dist-info/METADATA
ai_lab_dump-0.0.3.dist-info/WHEEL
ai_lab_dump-0.0.3.dist-info/top_level.txt
ai_lab_dump-0.0.3.dist-info/RECORD
