Metadata-Version: 2.1
Name: ai_lab_dump
Version: 0.0.3
Summary: basic algorithms and generic problem solutions
Author: The OA
Classifier: Programming Language :: Python :: 3
Classifier: License :: OSI Approved :: MIT License
Classifier: Operating System :: OS Independent
Requires-Python: >=3.6
License-File: LICENSE
